nevesdb/__init__.py
nevesdb/core/__init__.py
nevesdb/core/logger.py
nevesdb/core/model.py
nevesdb/core/nevesdb.py
nevesdb/core/adapters/__init__.py
nevesdb/core/adapters/adapter.py
nevesdb/core/adapters/mongo_db.py
nevesdb/core/adapters/sql_db.py
nevesdb-0.1.5.dist-info/LICENSE
nevesdb-0.1.5.dist-info/METADATA
nevesdb-0.1.5.dist-info/WHEEL
nevesdb-0.1.5.dist-info/top_level.txt
nevesdb-0.1.5.dist-info/RECORD
