Metadata-Version: 2.2
Name: nevesdb
Version: 0.1.5
Summary: A simple to use database abstraction layer
Author-email: Franklin Neves Filho <franklin.neves.filho@gmail.com>
License:                                  Apache License
Project-URL: Homepage, https://github.com/franklinnevesfilho/NevesDB
Project-URL: Repository, https://github.com/franklinnevesfilho/NevesDB
Project-URL: Issues, https://github.com/franklinnevesfilho/NevesDB/issues
Requires-Python: >=3.7
License-File: LICENSE
Requires-Dist: dnspython==2.7.0
Requires-Dist: greenlet==3.1.1
Requires-Dist: mysqlclient==2.2.7
Requires-Dist: pymongo==4.11.1
Requires-Dist: PyMySQL==1.1.1
Requires-Dist: SQLAlchemy==2.0.38
Requires-Dist: typing_extensions==4.12.2
